setup.py
hagraph/__init__.py
hagraph/__main__.py
hagraph.egg-info/PKG-INFO
hagraph.egg-info/SOURCES.txt
hagraph.egg-info/dependency_links.txt
hagraph.egg-info/entry_points.txt
hagraph.egg-info/requires.txt
hagraph.egg-info/top_level.txt