Metadata-Version: 1.1
Name: hagraph
Version: 1.0.3
Summary: Graph Home Assistant configurations
Home-page: https://github.com/happyleavesaoc/home-assistant-graph/
Author: happyleaves
Author-email: happyleaves.tfr@gmail.com
License: MIT
Platform: UNKNOWN
Classifier: License :: OSI Approved :: MIT License
Classifier: Operating System :: OS Independent
Classifier: Programming Language :: Python :: 3
